chow_test/__init__.py
chowtest_polars-0.0.1a3.dist-info/LICENSE
chowtest_polars-0.0.1a3.dist-info/METADATA
chowtest_polars-0.0.1a3.dist-info/WHEEL
chowtest_polars-0.0.1a3.dist-info/top_level.txt
chowtest_polars-0.0.1a3.dist-info/RECORD
