Metadata-Version: 2.1
Name: chowtest-polars
Version: 0.0.1a3
Author: Henkhogan
License: # License
Requires-Python: >=3.0
License-File: LICENSE
Requires-Dist: scikit-learn
Requires-Dist: scipy
Requires-Dist: polars
